docker_run_cmd/__init__.py
docker_run_cmd/api.py
docker_run_cmd/cli.py
docker_run_cmd/cli_start_docker.py
docker_run_cmd/assets/docker-compose-template.yml
docker_run_cmd/assets/example.txt
docker_run_cmd-1.0.14.dist-info/LICENSE
docker_run_cmd-1.0.14.dist-info/METADATA
docker_run_cmd-1.0.14.dist-info/WHEEL
docker_run_cmd-1.0.14.dist-info/entry_points.txt
docker_run_cmd-1.0.14.dist-info/top_level.txt
docker_run_cmd-1.0.14.dist-info/RECORD
