Metadata-Version: 2.1
Name: docker-run-cmd
Version: 1.0.14
Summary: Runs Dockerized commands
Home-page: https://github.com/zackees/docker-run-cmd
Maintainer: Zachary Vorhies
License: BSD 3-Clause License
Keywords: template-python-cmd
Classifier: Programming Language :: Python :: 3
Requires-Python: >=3.7
License-File: LICENSE
Requires-Dist: download
